{
  "WorkItem": {
    "AffectedComponent": {
      "Name": "",
      "DisplayName": ""
    },
    "ClosedComment": "",
    "ClosedDate": "2014-04-07T17:10:26.043-07:00",
    "CommentCount": 0,
    "Custom": "0.25 units",
    "Description": "Randy has reported the following issue:\n\n\"I just noticed that the Power Lines layer actually turns on streams, which are colored a pinkish color line.\"",
    "LastUpdatedDate": "2017-11-27T16:58:23.247-08:00",
    "PlannedForRelease": "Final Release Software",
    "ReleaseVisibleToPublic": false,
    "Priority": {
      "Name": "High",
      "Severity": 150,
      "Id": 3
    },
    "ProjectName": "pvmapper",
    "ReportedDate": "2014-03-31T09:02:40.993-07:00",
    "Status": {
      "Name": "Closed",
      "Id": 4
    },
    "ReasonClosed": {
      "Name": "Unassigned"
    },
    "Summary": "Power lines layer issue",
    "Type": {
      "Name": "Issue",
      "Id": 3
    },
    "VoteCount": 1,
    "Id": 25335
  },
  "FileAttachments": [],
  "Comments": [
    {
      "Message": "Resolved with changeset 74164: Removed erroneous \"power lines\" layer published by the nearest river tool.",
      "PostedDate": "2014-04-07T17:10:26.043-07:00",
      "Id": -2147483648
    },
    {
      "Message": "",
      "PostedDate": "2017-11-27T16:58:23.247-08:00",
      "Id": -2147483648
    }
  ]
}