{
  "WorkItem": {
    "AffectedComponent": {
      "Name": "",
      "DisplayName": ""
    },
    "ClosedComment": "",
    "ClosedDate": "2013-05-10T09:01:18.277-07:00",
    "CommentCount": 0,
    "Custom": "0.5 units",
    "Description": "Take the score weight and curve editing buttons from the left-hand bar, and add them to the new score board.",
    "LastUpdatedDate": "2017-11-27T16:56:45.6-08:00",
    "PlannedForRelease": "Solar 2013 Conference Demo",
    "ReleaseVisibleToPublic": false,
    "Priority": {
      "Name": "Medium",
      "Severity": 100,
      "Id": 2
    },
    "ProjectName": "pvmapper",
    "ReportedDate": "2013-02-14T18:14:33.66-08:00",
    "Status": {
      "Name": "Closed",
      "Id": 4
    },
    "ReasonClosed": {
      "Name": "Unassigned"
    },
    "Summary": "Add weight and score function adjustment buttons",
    "Type": {
      "Name": "Feature",
      "Id": 1
    },
    "VoteCount": 0,
    "Id": 23916
  },
  "FileAttachments": [],
  "Comments": [
    {
      "Message": "Associated with changeset 71867: Added the graph to the Utility Editor window. Hooked up the property grid to the graph using a cloned args object.",
      "PostedDate": "2013-04-14T20:30:22.69-07:00",
      "Id": -2147483648
    },
    {
      "Message": "",
      "PostedDate": "2013-05-10T09:01:18.277-07:00",
      "Id": -2147483648
    },
    {
      "Message": "",
      "PostedDate": "2013-05-15T19:28:25.307-07:00",
      "Id": -2147483648
    },
    {
      "Message": "",
      "PostedDate": "2017-11-27T16:56:45.6-08:00",
      "Id": -2147483648
    }
  ]
}